odoo8_addon_sale_automatic_workflow-8.0.0.3.0.99.dev38-py3.8-nspkg.pth
odoo_addons/sale_automatic_workflow/README.rst
odoo_addons/sale_automatic_workflow/__init__.py
odoo_addons/sale_automatic_workflow/__openerp__.py
odoo_addons/sale_automatic_workflow/automatic_workflow_data.xml
odoo_addons/sale_automatic_workflow/automatic_workflow_job.py
odoo_addons/sale_automatic_workflow/invoice.py
odoo_addons/sale_automatic_workflow/sale.py
odoo_addons/sale_automatic_workflow/sale_view.xml
odoo_addons/sale_automatic_workflow/sale_workflow.xml
odoo_addons/sale_automatic_workflow/sale_workflow_process.py
odoo_addons/sale_automatic_workflow/sale_workflow_process_view.xml
odoo_addons/sale_automatic_workflow/stock_move.py
odoo_addons/sale_automatic_workflow/stock_picking.py
odoo_addons/sale_automatic_workflow/i18n/am.po
odoo_addons/sale_automatic_workflow/i18n/ar.po
odoo_addons/sale_automatic_workflow/i18n/bg.po
odoo_addons/sale_automatic_workflow/i18n/bs.po
odoo_addons/sale_automatic_workflow/i18n/ca.po
odoo_addons/sale_automatic_workflow/i18n/ca_ES.po
odoo_addons/sale_automatic_workflow/i18n/cs.po
odoo_addons/sale_automatic_workflow/i18n/da.po
odoo_addons/sale_automatic_workflow/i18n/de.po
odoo_addons/sale_automatic_workflow/i18n/el_GR.po
odoo_addons/sale_automatic_workflow/i18n/en_GB.po
odoo_addons/sale_automatic_workflow/i18n/es.po
odoo_addons/sale_automatic_workflow/i18n/es_AR.po
odoo_addons/sale_automatic_workflow/i18n/es_CL.po
odoo_addons/sale_automatic_workflow/i18n/es_CO.po
odoo_addons/sale_automatic_workflow/i18n/es_CR.po
odoo_addons/sale_automatic_workflow/i18n/es_DO.po
odoo_addons/sale_automatic_workflow/i18n/es_EC.po
odoo_addons/sale_automatic_workflow/i18n/es_ES.po
odoo_addons/sale_automatic_workflow/i18n/es_MX.po
odoo_addons/sale_automatic_workflow/i18n/es_PE.po
odoo_addons/sale_automatic_workflow/i18n/es_PY.po
odoo_addons/sale_automatic_workflow/i18n/es_VE.po
odoo_addons/sale_automatic_workflow/i18n/et.po
odoo_addons/sale_automatic_workflow/i18n/fa.po
odoo8_addon_sale_automatic_workflow-8.0.0.3.0.99.dev38.dist-info/METADATA
odoo8_addon_sale_automatic_workflow-8.0.0.3.0.99.dev38.dist-info/WHEEL
odoo8_addon_sale_automatic_workflow-8.0.0.3.0.99.dev38.dist-info/namespace_packages.txt
odoo8_addon_sale_automatic_workflow-8.0.0.3.0.99.dev38.dist-info/top_level.txt
odoo8_addon_sale_automatic_workflow-8.0.0.3.0.99.dev38.dist-info/RECORD
